LICENSE
MANIFEST.in
README.md
VERSION
requirements.txt
setup.cfg
setup.py
dvdp.ha_433.egg-info/PKG-INFO
dvdp.ha_433.egg-info/SOURCES.txt
dvdp.ha_433.egg-info/dependency_links.txt
dvdp.ha_433.egg-info/entry_points.txt
dvdp.ha_433.egg-info/requires.txt
dvdp.ha_433.egg-info/top_level.txt
dvdp/ha_433/__init__.py
dvdp/ha_433/__main__.py
dvdp/ha_433/light.py
dvdp/recorder_433/__init__.py
dvdp/recorder_433/__main__.py
dvdp/transmitter_433/__init__.py
dvdp/transmitter_433/__main__.py
dvdp/transmitter_433/transmitter.py