Metadata-Version: 2.1
Name: dvdp.ha-433
Version: 0.1.8
Summary: Home assistant 433 MHz devices over MQTT.
Home-page: https://github.com/davidvdp/ha_433
Author: David van der Pol
Author-email: david@davidvanderpol.com
License: MIT
Download-URL: https://github.com/davidvdp/ha_433/archive/v0.1.8.tar.gz
Keywords: MQTT,Home,Assistant,433 MHz,KlikAanKlikUit,ASK
Platform: UNKNOWN
Classifier: Intended Audience :: Developers
Classifier: License :: OSI Approved :: MIT License
Classifier: Programming Language :: Python :: 3
Classifier: Programming Language :: Python :: 3.7
